sockjs/__init__.py
sockjs/exceptions.py
sockjs/protocol.py
sockjs/route.py
sockjs/session.py
sockjs/transports/__init__.py
sockjs/transports/base.py
sockjs/transports/eventsource.py
sockjs/transports/htmlfile.py
sockjs/transports/jsonp.py
sockjs/transports/rawwebsocket.py
sockjs/transports/utils.py
sockjs/transports/websocket.py
sockjs/transports/xhr_pooling.py
sockjs/transports/xhrstreaming.py
sockjs-0.13.0.dist-info/LICENSE
sockjs-0.13.0.dist-info/METADATA
sockjs-0.13.0.dist-info/WHEEL
sockjs-0.13.0.dist-info/top_level.txt
sockjs-0.13.0.dist-info/RECORD
