Metadata-Version: 2.1
Name: sockjs
Version: 0.13.0
Summary: SockJS server implementation for aiohttp.
Home-page: https://github.com/aio-libs/sockjs/
Author: Nikolay Kim
Author-email: fafhrd91@gmail.com
License: Apache 2
Classifier: License :: OSI Approved :: Apache Software License
Classifier: Intended Audience :: Developers
Classifier: Programming Language :: Python
Classifier: Programming Language :: Python :: 3
Classifier: Programming Language :: Python :: 3.10
Classifier: Programming Language :: Python :: 3.11
Classifier: Programming Language :: Python :: 3.12
Classifier: Programming Language :: Python :: Implementation :: CPython
Classifier: Topic :: Internet :: WWW/HTTP
Classifier: Framework :: AsyncIO
Requires-Python: >=3.10.0
License-File: LICENSE
Requires-Dist: aiohttp>=3.7.4
Requires-Dist: async-timeout>=4.0.3
Provides-Extra: test
Requires-Dist: pytest; extra == "test"
Requires-Dist: multidict; extra == "test"
Requires-Dist: yarl; extra == "test"
Requires-Dist: pytest-aiohttp; extra == "test"
Requires-Dist: pytest-mock; extra == "test"
Requires-Dist: pytest-timeout; extra == "test"
Requires-Dist: cykooz.testing; extra == "test"
Requires-Dist: aiohttp_cors; extra == "test"
